pocketbase/__init__.py
pocketbase/client.py
pocketbase/models/__init__.py
pocketbase/models/dtos.py
pocketbase/models/errors.py
pocketbase/models/options.py
pocketbase/py.typed
pocketbase/services/__init__.py
pocketbase/services/authorization.py
pocketbase/services/backup.py
pocketbase/services/base.py
pocketbase/services/collection.py
pocketbase/services/crud.py
pocketbase/services/file.py
pocketbase/services/health.py
pocketbase/services/log.py
pocketbase/services/realtime.py
pocketbase/services/record.py
pocketbase/utils/__init__.py
pocketbase/utils/filter.py
pocketbase/utils/types.py
pocketbase_async-0.12.0.dist-info/LICENSE.txt
pocketbase_async-0.12.0.dist-info/METADATA
pocketbase_async-0.12.0.dist-info/WHEEL
pocketbase_async-0.12.0.dist-info/RECORD
