Metadata-Version: 2.3
Name: pocketbase-async
Version: 0.12.0
Summary: Async pocketbase SDK for Python
License: MIT
Author: Thijs Miedema
Author-email: opensource@tmiedema.com
Requires-Python: >=3.11,<3.14
Classifier: Intended Audience :: Developers
Classifier: License :: OSI Approved :: MIT License
Classifier: Natural Language :: English
Classifier: Operating System :: OS Independent
Classifier: Programming Language :: Python
Classifier: Programming Language :: Python :: 3
Classifier: Programming Language :: Python :: 3.11
Classifier: Programming Language :: Python :: 3.12
Classifier: Programming Language :: Python :: 3.13
Requires-Dist: httpx (>=0.25.1,<1)
Requires-Dist: httpx-sse (>=0.4.0,<1)
Project-URL: Repository, https://github.com/thijsmie/pocketbase-async
